{
  "version": "4.5.6",
  "flags": {},
  "shapes": [
    {
      "rotated_box": [
        74.0,
        76.5,
        35.0,
        20.0,
        -90.0
      ],
      "label": "0:inhibit_body:",
      "points": [
        [
          71.0,
          59.0
        ],
        [
          71.0,
          94.0
        ],
        [
          160.0,
          94.0
        ],
        [
          160.0,
          59.0
        ]
      ],
      "group_id": null,
      "shape_type": "polygon",
      "flags": {}
    },
    {
      "rotated_box": [
        164.50001525878906,
        75.5,
        26.829822540283203,
        30.367090225219727,
        -64.29004669189453
      ],
      "label": "1:inhibit_body:",
      "points": [
        [
          155.0,
          62.0
        ],
        [
          155.0,
          88.0
        ],
        [
          182.0,
          88.0
        ],
        [
          182.0,
          62.0
        ]
      ],
      "group_id": null,
      "shape_type": "polygon",
      "flags": {}
    },
    {
      "rotated_box": [
        383.0,
        76.5,
        35.0,
        20.0,
        -90.0
      ],
      "label": "2:inhibit_body:",
      "points": [
        [
          380.0,
          60.0
        ],
        [
          380.0,
          95.0
        ],
        [
          437.0,
          95.0
        ],
        [
          437.0,
          60.0
        ]
      ],
      "group_id": null,
      "shape_type": "polygon",
      "flags": {}
    },
    {
      "rotated_box": [
        297.0,
        78.5,
        29.0,
        20.0,
        -90.0
      ],
      "label": "3:inhibit_body:",
      "points": [
        [
          293.0,
          65.0
        ],
        [
          293.0,
          94.0
        ],
        [
          313.0,
          94.0
        ],
        [
          313.0,
          65.0
        ]
      ],
      "group_id": null,
      "shape_type": "polygon",
      "flags": {}
    },
    {
      "rotated_box": [
        92.22124481201172,
        135.18141174316406,
        22.29726791381836,
        23.769731521606445,
        -67.7509765625
      ],
      "label": "4:activate_body:",
      "points": [
        [
          79.0,
          125.0
        ],
        [
          79.0,
          148.0
        ],
        [
          99.0,
          148.0
        ],
        [
          99.0,
          125.0
        ]
      ],
      "group_id": null,
      "shape_type": "polygon",
      "flags": {}
    },
    {
      "rotated_box": [
        178.5,
        140.0,
        41.0,
        20.0,
        0.0
      ],
      "label": "5:gene:",
      "points": [
        [
          158.0,
          130.0
        ],
        [
          158.0,
          150.0
        ],
        [
          199.0,
          150.0
        ],
        [
          199.0,
          130.0
        ]
      ],
      "group_id": null,
      "shape_type": "polygon",
      "flags": {}
    },
    {
      "rotated_box": [
        38.5,
        145.0,
        24.0,
        19.0,
        -90.0
      ],
      "label": "6:activate_body:",
      "points": [
        [
          28.0,
          137.0
        ],
        [
          28.0,
          156.0
        ],
        [
          47.0,
          156.0
        ],
        [
          47.0,
          137.0
        ]
      ],
      "group_id": null,
      "shape_type": "polygon",
      "flags": {}
    },
    {
      "rotated_box": [
        214.5,
        161.0,
        22.0,
        21.0,
        -90.0
      ],
      "label": "7:activate_body:",
      "points": [
        [
          204.0,
          150.0
        ],
        [
          204.0,
          184.0
        ],
        [
          263.0,
          184.0
        ],
        [
          263.0,
          150.0
        ]
      ],
      "group_id": null,
      "shape_type": "polygon",
      "flags": {}
    },
    {
      "rotated_box": [
        324.0,
        171.5,
        19.0,
        18.0,
        -90.0
      ],
      "label": "8:activate_body:",
      "points": [
        [
          312.0,
          161.0
        ],
        [
          312.0,
          192.0
        ],
        [
          363.0,
          192.0
        ],
        [
          363.0,
          161.0
        ]
      ],
      "group_id": null,
      "shape_type": "polygon",
      "flags": {}
    },
    {
      "rotated_box": [
        131.50001525878906,
        167.5,
        26.570571899414062,
        29.799400329589844,
        -70.34617614746094
      ],
      "label": "9:inhibit_body:",
      "points": [
        [
          124.0,
          155.0
        ],
        [
          124.0,
          183.0
        ],
        [
          171.0,
          183.0
        ],
        [
          171.0,
          155.0
        ]
      ],
      "group_id": null,
      "shape_type": "polygon",
      "flags": {}
    },
    {
      "rotated_box": [
        99.85145568847656,
        211.29444885253906,
        27.459060668945312,
        17.55340576171875,
        -56.88865280151367
      ],
      "label": "10:activate_body:",
      "points": [
        [
          89.0,
          196.0
        ],
        [
          89.0,
          217.0
        ],
        [
          110.0,
          217.0
        ],
        [
          110.0,
          196.0
        ]
      ],
      "group_id": null,
      "shape_type": "polygon",
      "flags": {}
    },
    {
      "rotated_box": [
        443.0,
        181.0,
        30.0,
        20.0,
        -90.0
      ],
      "label": "11:inhibit_body:",
      "points": [
        [
          425.0,
          169.0
        ],
        [
          425.0,
          196.0
        ],
        [
          447.0,
          196.0
        ],
        [
          447.0,
          169.0
        ]
      ],
      "group_id": null,
      "shape_type": "polygon",
      "flags": {}
    },
    {
      "rotated_box": [
        211.2341766357422,
        189.61895751953125,
        20.200376510620117,
        23.89986228942871,
        -86.633544921875
      ],
      "label": "12:activate_body:",
      "points": [
        [
          200.0,
          160.0
        ],
        [
          200.0,
          199.0
        ],
        [
          261.0,
          199.0
        ],
        [
          261.0,
          160.0
        ]
      ],
      "group_id": null,
      "shape_type": "polygon",
      "flags": {}
    },
    {
      "rotated_box": [
        519.0,
        191.0,
        20.0,
        16.0,
        -90.0
      ],
      "label": "13:activate_body:",
      "points": [
        [
          511.0,
          164.0
        ],
        [
          511.0,
          201.0
        ],
        [
          534.0,
          201.0
        ],
        [
          534.0,
          164.0
        ]
      ],
      "group_id": null,
      "shape_type": "polygon",
      "flags": {}
    },
    {
      "rotated_box": [
        36.0,
        205.49998474121094,
        18.167997360229492,
        29.781265258789062,
        -4.085616588592529
      ],
      "label": "14:activate_body:",
      "points": [
        [
          31.0,
          196.0
        ],
        [
          31.0,
          216.0
        ],
        [
          48.0,
          216.0
        ],
        [
          48.0,
          196.0
        ]
      ],
      "group_id": null,
      "shape_type": "polygon",
      "flags": {}
    },
    {
      "rotated_box": [
        50.5,
        200.0,
        20.0,
        31.0,
        -90.0
      ],
      "label": "15:inhibit_body:",
      "points": [
        [
          37.0,
          187.0
        ],
        [
          37.0,
          205.0
        ],
        [
          68.0,
          205.0
        ],
        [
          68.0,
          187.0
        ]
      ],
      "group_id": null,
      "shape_type": "polygon",
      "flags": {}
    },
    {
      "rotated_box": [
        509.05950927734375,
        32.32471466064453,
        47.686553955078125,
        76.0592041015625,
        -87.73949432373047
      ],
      "label": "16:gene:NF-ICB",
      "points": [
        [
          472.0,
          7.0
        ],
        [
          472.0,
          57.0
        ],
        [
          548.0,
          57.0
        ],
        [
          548.0,
          7.0
        ]
      ],
      "group_id": null,
      "shape_type": "polygon",
      "flags": {}
    },
    {
      "rotated_box": [
        73.5,
        28.0,
        26.0,
        73.0,
        -90.0
      ],
      "label": "17:gene:EGFR-Ab",
      "points": [
        [
          37.0,
          15.0
        ],
        [
          37.0,
          41.0
        ],
        [
          110.0,
          41.0
        ],
        [
          110.0,
          15.0
        ]
      ],
      "group_id": null,
      "shape_type": "polygon",
      "flags": {}
    },
    {
      "rotated_box": [
        288.5,
        40.5,
        25.0,
        81.0,
        -90.0
      ],
      "label": "18:gene:LY294-002",
      "points": [
        [
          248.0,
          28.0
        ],
        [
          248.0,
          53.0
        ],
        [
          329.0,
          53.0
        ],
        [
          329.0,
          28.0
        ]
      ],
      "group_id": null,
      "shape_type": "polygon",
      "flags": {}
    },
    {
      "rotated_box": [
        374.4999694824219,
        40.5,
        60.99999237060547,
        22.999996185302734,
        0.0
      ],
      "label": "19:gene:604976",
      "points": [
        [
          344.0,
          29.0
        ],
        [
          344.0,
          52.0
        ],
        [
          405.0,
          52.0
        ],
        [
          405.0,
          29.0
        ]
      ],
      "group_id": null,
      "shape_type": "polygon",
      "flags": {}
    },
    {
      "rotated_box": [
        287.0,
        64.49999237060547,
        26.179067611694336,
        21.063159942626953,
        -87.70938873291016
      ],
      "label": "20:inhibit_body:",
      "points": [
        [
          276.0,
          51.0
        ],
        [
          276.0,
          77.0
        ],
        [
          294.0,
          77.0
        ],
        [
          294.0,
          51.0
        ]
      ],
      "group_id": null,
      "shape_type": "polygon",
      "flags": {}
    },
    {
      "rotated_box": [
        225.0,
        77.0,
        26.0,
        84.0,
        -90.0
      ],
      "label": "21:gene:-I P13 Kinase",
      "points": [
        [
          186.0,
          65.0
        ],
        [
          186.0,
          91.0
        ],
        [
          270.0,
          91.0
        ],
        [
          270.0,
          65.0
        ]
      ],
      "group_id": null,
      "shape_type": "polygon",
      "flags": {}
    },
    {
      "rotated_box": [
        492.0,
        83.0,
        54.0,
        24.0,
        0.0
      ],
      "label": "22:gene:-M",
      "points": [
        [
          465.0,
          71.0
        ],
        [
          465.0,
          95.0
        ],
        [
          519.0,
          95.0
        ],
        [
          519.0,
          71.0
        ]
      ],
      "group_id": null,
      "shape_type": "polygon",
      "flags": {}
    },
    {
      "rotated_box": [
        511.4888916015625,
        135.4071807861328,
        43.86100769042969,
        65.06919860839844,
        -87.35746002197266
      ],
      "label": "23:gene:YACtIVeNF-KBJ",
      "points": [
        [
          480.0,
          112.0
        ],
        [
          480.0,
          156.0
        ],
        [
          545.0,
          156.0
        ],
        [
          545.0,
          112.0
        ]
      ],
      "group_id": null,
      "shape_type": "polygon",
      "flags": {}
    },
    {
      "rotated_box": [
        391.0,
        209.5,
        25.0,
        54.0,
        -90.0
      ],
      "label": "24:gene:C dk4l6",
      "points": [
        [
          364.0,
          197.0
        ],
        [
          364.0,
          222.0
        ],
        [
          418.0,
          222.0
        ],
        [
          418.0,
          197.0
        ]
      ],
      "group_id": null,
      "shape_type": "polygon",
      "flags": {}
    },
    {
      "rotated_box": [
        28.0,
        77.5,
        25.0,
        36.0,
        -90.0
      ],
      "label": "25:gene:",
      "points": [
        [
          10.0,
          65.0
        ],
        [
          10.0,
          90.0
        ],
        [
          46.0,
          90.0
        ],
        [
          46.0,
          65.0
        ]
      ],
      "group_id": null,
      "shape_type": "polygon",
      "flags": {}
    },
    {
      "rotated_box": [
        56.0,
        156.5,
        17.0,
        20.0,
        -90.0
      ],
      "label": "26:gene:",
      "points": [
        [
          46.0,
          148.0
        ],
        [
          46.0,
          165.0
        ],
        [
          66.0,
          165.0
        ],
        [
          66.0,
          148.0
        ]
      ],
      "group_id": null,
      "shape_type": "polygon",
      "flags": {}
    },
    {
      "rotated_box": [
        89.5,
        159.5,
        15.0,
        23.0,
        -90.0
      ],
      "label": "27:gene:",
      "points": [
        [
          78.0,
          152.0
        ],
        [
          78.0,
          167.0
        ],
        [
          101.0,
          167.0
        ],
        [
          101.0,
          152.0
        ]
      ],
      "group_id": null,
      "shape_type": "polygon",
      "flags": {}
    },
    {
      "rotated_box": [
        176.0,
        211.5,
        19.0,
        36.0,
        -90.0
      ],
      "label": "28:gene:",
      "points": [
        [
          158.0,
          202.0
        ],
        [
          158.0,
          221.0
        ],
        [
          194.0,
          221.0
        ],
        [
          194.0,
          202.0
        ]
      ],
      "group_id": null,
      "shape_type": "polygon",
      "flags": {}
    },
    {
      "rotated_box": [
        287.5,
        192.5,
        19.0,
        33.0,
        -90.0
      ],
      "label": "29:gene:",
      "points": [
        [
          271.0,
          183.0
        ],
        [
          271.0,
          202.0
        ],
        [
          304.0,
          202.0
        ],
        [
          304.0,
          183.0
        ]
      ],
      "group_id": null,
      "shape_type": "polygon",
      "flags": {}
    },
    {
      "rotated_box": [
        288.5,
        163.0,
        18.0,
        25.0,
        -90.0
      ],
      "label": "30:gene:",
      "points": [
        [
          276.0,
          154.0
        ],
        [
          276.0,
          172.0
        ],
        [
          301.0,
          172.0
        ],
        [
          301.0,
          154.0
        ]
      ],
      "group_id": null,
      "shape_type": "polygon",
      "flags": {}
    },
    {
      "rotated_box": [
        390.0,
        180.0,
        20.0,
        42.0,
        -90.0
      ],
      "label": "31:gene:",
      "points": [
        [
          369.0,
          170.0
        ],
        [
          369.0,
          192.0
        ],
        [
          411.0,
          192.0
        ],
        [
          411.0,
          170.0
        ]
      ],
      "group_id": null,
      "shape_type": "polygon",
      "flags": {}
    },
    {
      "rotated_box": [
        487.5,
        217.64413452148438,
        40.99999237060547,
        17.999996185302734,
        0.0
      ],
      "label": "32:gene:",
      "points": [
        [
          467.0,
          209.0
        ],
        [
          467.0,
          227.0
        ],
        [
          508.0,
          227.0
        ],
        [
          508.0,
          209.0
        ]
      ],
      "group_id": null,
      "shape_type": "polygon",
      "flags": {}
    },
    {
      "rotated_box": [
        339.5,
        78.5,
        15.0,
        35.0,
        -90.0
      ],
      "label": "34:gene:",
      "points": [
        [
          322.0,
          71.0
        ],
        [
          322.0,
          86.0
        ],
        [
          357.0,
          86.0
        ],
        [
          357.0,
          71.0
        ]
      ],
      "group_id": null,
      "shape_type": "polygon",
      "flags": {}
    },
    {
      "rotated_box": [
        417.5,
        77.5,
        21.0,
        31.0,
        -90.0
      ],
      "label": "35:gene:",
      "points": [
        [
          402.0,
          67.0
        ],
        [
          402.0,
          88.0
        ],
        [
          433.0,
          88.0
        ],
        [
          433.0,
          67.0
        ]
      ],
      "group_id": null,
      "shape_type": "polygon",
      "flags": {}
    },
    {
      "rotated_box": [
        63.0,
        62.5,
        29.0,
        18.0,
        -90.0
      ],
      "label": "36:inhibit_body:",
      "points": [
        [
          53.0,
          47.0
        ],
        [
          53.0,
          74.0
        ],
        [
          69.0,
          74.0
        ],
        [
          69.0,
          47.0
        ]
      ],
      "group_id": null,
      "shape_type": "polygon",
      "flags": {}
    },
    {
      "rotated_box": [
        375.0,
        63.0,
        28.0,
        16.0,
        -90.0
      ],
      "label": "37:inhibit_body:",
      "points": [
        [
          365.0,
          50.0
        ],
        [
          365.0,
          76.0
        ],
        [
          380.0,
          76.0
        ],
        [
          380.0,
          50.0
        ]
      ],
      "group_id": null,
      "shape_type": "polygon",
      "flags": {}
    },
    {
      "rotated_box": [
        453.5,
        80.0,
        18.0,
        27.0,
        -90.0
      ],
      "label": "38:inhibit_body:22|35",
      "points": [
        [
          440.0,
          71.0
        ],
        [
          440.0,
          89.0
        ],
        [
          467.0,
          89.0
        ],
        [
          467.0,
          71.0
        ]
      ],
      "group_id": null,
      "shape_type": "polygon",
      "flags": {}
    },
    {
      "rotated_box": [
        461.0,
        132.0,
        64.0,
        36.0,
        -90.0
      ],
      "label": "39:activate_body:16|23",
      "points": [
        [
          382.0,
          19.0
        ],
        [
          382.0,
          164.0
        ],
        [
          479.0,
          164.0
        ],
        [
          479.0,
          19.0
        ]
      ],
      "group_id": null,
      "shape_type": "polygon",
      "flags": {}
    },
    {
      "rotated_box": [
        460.4752197265625,
        81.53372192382812,
        26.483007431030273,
        118.174560546875,
        -87.33700561523438
      ],
      "label": "40:inhibit_relation:22|35",
      "points": [
        [
          518.8834228515625,
          97.50619506835938
        ],
        [
          400.8365173339844,
          92.01565551757812
        ],
        [
          402.06695556640625,
          65.56124877929688
        ],
        [
          520.1138916015625,
          71.05178833007812
        ]
      ],
      "group_id": null,
      "shape_type": "polygon",
      "flags": {}
    },
    {
      "rotated_box": [
        494.6066589355469,
        86.06436920166016,
        166.95201110839844,
        94.61305236816406,
        -88.37887573242188
      ],
      "label": "41:activate_relation:16|23",
      "points": [
        [
          539.53271484375,
          170.84527587890625
        ],
        [
          445.1901550292969,
          159.94879150390625
        ],
        [
          449.6806640625,
          1.283447265625
        ],
        [
          544.023193359375,
          12.179931640625
        ]
      ],
      "group_id": null,
      "shape_type": "polygon",
      "flags": {}
    },
    {
      "label": "0:inhibit_head:",
      "points": [
        [
          64.0,
          59.0
        ],
        [
          64.0,
          94.0
        ],
        [
          84.0,
          94.0
        ],
        [
          84.0,
          59.0
        ]
      ],
      "group_id": null,
      "shape_type": "polygon",
      "flags": {},
      "rotated_box": [
        74.0,
        76.5,
        35.0,
        20.0,
        -90.0
      ]
    },
    {
      "label": "1:inhibit_head:",
      "points": [
        [
          145.0,
          57.0
        ],
        [
          145.0,
          94.0
        ],
        [
          184.0,
          94.0
        ],
        [
          184.0,
          57.0
        ]
      ],
      "group_id": null,
      "shape_type": "polygon",
      "flags": {},
      "rotated_box": [
        164.50001525878906,
        75.5,
        26.829822540283203,
        30.367090225219727,
        -64.29004669189453
      ]
    },
    {
      "label": "2:inhibit_head:",
      "points": [
        [
          373.0,
          59.0
        ],
        [
          373.0,
          94.0
        ],
        [
          393.0,
          94.0
        ],
        [
          393.0,
          59.0
        ]
      ],
      "group_id": null,
      "shape_type": "polygon",
      "flags": {},
      "rotated_box": [
        383.0,
        76.5,
        35.0,
        20.0,
        -90.0
      ]
    },
    {
      "label": "3:inhibit_head:",
      "points": [
        [
          287.0,
          64.0
        ],
        [
          287.0,
          93.0
        ],
        [
          307.0,
          93.0
        ],
        [
          307.0,
          64.0
        ]
      ],
      "group_id": null,
      "shape_type": "polygon",
      "flags": {},
      "rotated_box": [
        297.0,
        78.5,
        29.0,
        20.0,
        -90.0
      ]
    },
    {
      "label": "4:activate_head:",
      "points": [
        [
          77.0,
          121.0
        ],
        [
          77.0,
          150.0
        ],
        [
          104.0,
          150.0
        ],
        [
          104.0,
          121.0
        ]
      ],
      "group_id": null,
      "shape_type": "polygon",
      "flags": {},
      "rotated_box": [
        92.22124481201172,
        135.18141174316406,
        22.29726791381836,
        23.769731521606445,
        -67.7509765625
      ]
    },
    {
      "label": "6:activate_head:",
      "points": [
        [
          29.0,
          133.0
        ],
        [
          29.0,
          157.0
        ],
        [
          48.0,
          157.0
        ],
        [
          48.0,
          133.0
        ]
      ],
      "group_id": null,
      "shape_type": "polygon",
      "flags": {},
      "rotated_box": [
        38.5,
        145.0,
        24.0,
        19.0,
        -90.0
      ]
    },
    {
      "label": "7:activate_head:",
      "points": [
        [
          204.0,
          150.0
        ],
        [
          204.0,
          172.0
        ],
        [
          225.0,
          172.0
        ],
        [
          225.0,
          150.0
        ]
      ],
      "group_id": null,
      "shape_type": "polygon",
      "flags": {},
      "rotated_box": [
        214.5,
        161.0,
        22.0,
        21.0,
        -90.0
      ]
    },
    {
      "label": "8:activate_head:",
      "points": [
        [
          315.0,
          162.0
        ],
        [
          315.0,
          181.0
        ],
        [
          333.0,
          181.0
        ],
        [
          333.0,
          162.0
        ]
      ],
      "group_id": null,
      "shape_type": "polygon",
      "flags": {},
      "rotated_box": [
        324.0,
        171.5,
        19.0,
        18.0,
        -90.0
      ]
    },
    {
      "label": "9:inhibit_head:",
      "points": [
        [
          113.0,
          150.0
        ],
        [
          113.0,
          185.0
        ],
        [
          150.0,
          185.0
        ],
        [
          150.0,
          150.0
        ]
      ],
      "group_id": null,
      "shape_type": "polygon",
      "flags": {},
      "rotated_box": [
        131.50001525878906,
        167.5,
        26.570571899414062,
        29.799400329589844,
        -70.34617614746094
      ]
    },
    {
      "label": "10:activate_head:",
      "points": [
        [
          85.0,
          195.0
        ],
        [
          85.0,
          221.0
        ],
        [
          113.0,
          221.0
        ],
        [
          113.0,
          195.0
        ]
      ],
      "group_id": null,
      "shape_type": "polygon",
      "flags": {},
      "rotated_box": [
        99.85145568847656,
        211.29444885253906,
        27.459060668945312,
        17.55340576171875,
        -56.88865280151367
      ]
    },
    {
      "label": "11:inhibit_head:",
      "points": [
        [
          433.0,
          166.0
        ],
        [
          433.0,
          196.0
        ],
        [
          453.0,
          196.0
        ],
        [
          453.0,
          166.0
        ]
      ],
      "group_id": null,
      "shape_type": "polygon",
      "flags": {},
      "rotated_box": [
        443.0,
        181.0,
        30.0,
        20.0,
        -90.0
      ]
    },
    {
      "label": "12:activate_head:",
      "points": [
        [
          199.0,
          179.0
        ],
        [
          199.0,
          199.0
        ],
        [
          224.0,
          199.0
        ],
        [
          224.0,
          179.0
        ]
      ],
      "group_id": null,
      "shape_type": "polygon",
      "flags": {},
      "rotated_box": [
        211.2341766357422,
        189.61895751953125,
        20.200376510620117,
        23.89986228942871,
        -86.633544921875
      ]
    },
    {
      "label": "13:activate_head:",
      "points": [
        [
          511.0,
          181.0
        ],
        [
          511.0,
          201.0
        ],
        [
          527.0,
          201.0
        ],
        [
          527.0,
          181.0
        ]
      ],
      "group_id": null,
      "shape_type": "polygon",
      "flags": {},
      "rotated_box": [
        519.0,
        191.0,
        20.0,
        16.0,
        -90.0
      ]
    },
    {
      "label": "14:activate_head:",
      "points": [
        [
          26.0,
          190.0
        ],
        [
          26.0,
          221.0
        ],
        [
          44.0,
          221.0
        ],
        [
          44.0,
          190.0
        ]
      ],
      "group_id": null,
      "shape_type": "polygon",
      "flags": {},
      "rotated_box": [
        36.0,
        205.49998474121094,
        18.167997360229492,
        29.781265258789062,
        -4.085616588592529
      ]
    },
    {
      "label": "15:inhibit_head:",
      "points": [
        [
          35.0,
          190.0
        ],
        [
          35.0,
          210.0
        ],
        [
          66.0,
          210.0
        ],
        [
          66.0,
          190.0
        ]
      ],
      "group_id": null,
      "shape_type": "polygon",
      "flags": {},
      "rotated_box": [
        50.5,
        200.0,
        20.0,
        31.0,
        -90.0
      ]
    },
    {
      "label": "20:inhibit_head:",
      "points": [
        [
          276.0,
          51.0
        ],
        [
          276.0,
          78.0
        ],
        [
          297.0,
          78.0
        ],
        [
          297.0,
          51.0
        ]
      ],
      "group_id": null,
      "shape_type": "polygon",
      "flags": {},
      "rotated_box": [
        287.0,
        64.49999237060547,
        26.179067611694336,
        21.063159942626953,
        -87.70938873291016
      ]
    },
    {
      "label": "36:inhibit_head:",
      "points": [
        [
          54.0,
          48.0
        ],
        [
          54.0,
          77.0
        ],
        [
          72.0,
          77.0
        ],
        [
          72.0,
          48.0
        ]
      ],
      "group_id": null,
      "shape_type": "polygon",
      "flags": {},
      "rotated_box": [
        63.0,
        62.5,
        29.0,
        18.0,
        -90.0
      ]
    },
    {
      "label": "37:inhibit_head:",
      "points": [
        [
          367.0,
          49.0
        ],
        [
          367.0,
          77.0
        ],
        [
          383.0,
          77.0
        ],
        [
          383.0,
          49.0
        ]
      ],
      "group_id": null,
      "shape_type": "polygon",
      "flags": {},
      "rotated_box": [
        375.0,
        63.0,
        28.0,
        16.0,
        -90.0
      ]
    },
    {
      "label": "38:inhibit_head:22|35",
      "points": [
        [
          440.0,
          71.0
        ],
        [
          440.0,
          89.0
        ],
        [
          467.0,
          89.0
        ],
        [
          467.0,
          71.0
        ]
      ],
      "group_id": null,
      "shape_type": "polygon",
      "flags": {},
      "rotated_box": [
        453.5,
        80.0,
        18.0,
        27.0,
        -90.0
      ]
    },
    {
      "label": "39:activate_head:16|23",
      "points": [
        [
          443.0,
          100.0
        ],
        [
          443.0,
          164.0
        ],
        [
          479.0,
          164.0
        ],
        [
          479.0,
          100.0
        ]
      ],
      "group_id": null,
      "shape_type": "polygon",
      "flags": {},
      "rotated_box": [
        461.0,
        132.0,
        64.0,
        36.0,
        -90.0
      ]
    }
  ],
  "lineColor": [
    0,
    255,
    0,
    128
  ],
  "fillColor": [
    255,
    0,
    0,
    128
  ],
  "imagePath": "aug4sim_inhibit__pmc_articles_instance_26984_bin_pq1502253001.jpg",
  "imageData": null,
  "imageHeight": 242,
  "imageWidth": 550
}